BackupService/__main__.py
BackupService/api.py
BackupService/const.py
BackupService/robocopy_config_creator.py
BackupService/service.py
pih_backup-0.22.dist-info/METADATA
pih_backup-0.22.dist-info/WHEEL
pih_backup-0.22.dist-info/entry_points.txt
pih_backup-0.22.dist-info/top_level.txt
pih_backup-0.22.dist-info/RECORD
