Metadata-Version: 2.1
Name: pih-backup
Version: 0.22
Summary: PIH Backup service package
Home-page: https://pacifichosp.com/
Author: Nikita Karachentsev
Author-email: it@pacifichosp.com
License: MIT
Requires-Dist: ipih
